asimov_universe/__init__.py
asimov_universe-25.0.0.dev0.dist-info/METADATA
asimov_universe-25.0.0.dev0.dist-info/WHEEL
asimov_universe-25.0.0.dev0.dist-info/top_level.txt
asimov_universe-25.0.0.dev0.dist-info/RECORD
