Metadata-Version: 2.2
Name: asimov-universe
Version: 25.0.0.dev0
Summary: ASIMOV Universe for Python
Author-email: ASIMOV Protocol <support@asimov.so>
License: Unlicense
Project-URL: Homepage, https://github.com/asimov-platform/asimov-universe.py
Project-URL: Documentation, https://github.com/asimov-platform/asimov-universe.py
Project-URL: Repository, https://github.com/asimov-platform/asimov-universe.py.git
Project-URL: Issues, https://github.com/asimov-platform/asimov-universe.py/issues
Project-URL: Changelog, https://github.com/asimov-platform/asimov-universe.py/blob/master/CHANGES.md
Classifier: Development Status :: 3 - Alpha
Classifier: Environment :: Console
Classifier: Environment :: MacOS X
Classifier: Intended Audience :: Developers
Classifier: License :: OSI Approved :: The Unlicense (Unlicense)
Classifier: License :: Public Domain
Classifier: Operating System :: MacOS :: MacOS X
Classifier: Programming Language :: Python :: 3
Classifier: Programming Language :: Python :: 3.13
Classifier: Programming Language :: Python :: 3.14
Classifier: Topic :: Scientific/Engineering :: Artificial Intelligence
Classifier: Topic :: Text Processing :: General
Requires-Python: >=3.13
Requires-Dist: asimov-modules
